requests_futures/__init__.py
requests_futures/sessions.py
requests_futures-1.0.2.dist-info/LICENSE
requests_futures-1.0.2.dist-info/METADATA
requests_futures-1.0.2.dist-info/WHEEL
requests_futures-1.0.2.dist-info/top_level.txt
requests_futures-1.0.2.dist-info/RECORD
